ADLES-1.4.0.data/data/man/man1/adles.1
adles/__about__.py
adles/__init__.py
adles/__main__.py
adles/args.py
adles/group.py
adles/main.py
adles/parser.py
adles/utils.py
adles/interfaces/__init__.py
adles/interfaces/cloud_interface.py
adles/interfaces/docker_interface.py
adles/interfaces/interface.py
adles/interfaces/libcloud_interface.py
adles/interfaces/platform_interface.py
adles/interfaces/vsphere_interface.py
adles/scripts/__init__.py
adles/scripts/script_base.py
adles/vsphere/__init__.py
adles/vsphere/__main__.py
adles/vsphere/folder_utils.py
adles/vsphere/host.py
adles/vsphere/network_utils.py
adles/vsphere/vm.py
adles/vsphere/vsphere_class.py
adles/vsphere/vsphere_scripts.py
adles/vsphere/vsphere_utils.py
examples/blue-teams.json
examples/competition-with-docker.yaml
examples/competition.yaml
examples/edurange_total-recon.yaml
examples/experiment.yaml
examples/firewall-tutorial.yaml
examples/infra.yaml
examples/pentest-tutorial.yaml
examples/spoofing-tutorial.yaml
examples/tutorial_instructors.json
examples/users.json
specifications/exercise-specification.yaml
specifications/infrastructure-specification.yaml
specifications/package-specification.yaml
specifications/user-spec.json
specifications/user-template-spec.json
ADLES-1.4.0.dist-info/LICENSE
ADLES-1.4.0.dist-info/METADATA
ADLES-1.4.0.dist-info/NOTICE
ADLES-1.4.0.dist-info/WHEEL
ADLES-1.4.0.dist-info/entry_points.txt
ADLES-1.4.0.dist-info/top_level.txt
ADLES-1.4.0.dist-info/RECORD
