Metadata-Version: 2.1
Name: ADLES
Version: 1.4.0
Summary: Automated Deployment of Lab Environments System (ADLES)
Home-page: https://github.com/GhostofGoes/ADLES
Author: Christopher Goes
Author-email: goesc@acm.org
License: Apache 2.0
Project-URL: GitHub, https://github.com/GhostofGoes/ADLES
Project-URL: Homepage, https://ghostofgoes.github.io/ADLES/
Project-URL: Documentation, https://adles.readthedocs.io
Project-URL: Publication, https://doi.org/10.1016/j.cose.2017.12.007
Project-URL: Discord server, https://discord.gg/python
Project-URL: Issue tracker, https://github.com/GhostofGoes/ADLES/issues
Keywords: virtualization,vmware,vsphere,cybersecurity,education,radicl
Platform: UNKNOWN
Classifier: Development Status :: 4 - Beta
Classifier: Environment :: Console
Classifier: License :: OSI Approved :: Apache Software License
Classifier: Operating System :: OS Independent
Classifier: Operating System :: Microsoft :: Windows
Classifier: Operating System :: POSIX
Classifier: Operating System :: MacOS
Classifier: Programming Language :: Python
Classifier: Programming Language :: Python :: 3
Classifier: Programming Language :: Python :: 3.6
Classifier: Programming Language :: Python :: 3.7
Classifier: Intended Audience :: Education
Classifier: Intended Audience :: Developers
Classifier: Intended Audience :: System Administrators
Classifier: Intended Audience :: Information Technology
Classifier: Intended Audience :: Science/Research
Classifier: Intended Audience :: End Users/Desktop
Classifier: Topic :: Education
Classifier: Topic :: Education :: Testing
Classifier: Topic :: Security
Classifier: Topic :: System :: Distributed Computing
Classifier: Topic :: System :: Systems Administration
Classifier: Topic :: Utilities
Requires-Python: >=3.6
Requires-Dist: pyyaml (==5.1.2)
Requires-Dist: colorlog (==3.1.4)
Requires-Dist: tqdm (==4.19.6)
Requires-Dist: humanfriendly (<5,>=4.12.1)
Requires-Dist: pyvmomi (<7.0.0,>=6.5)
Provides-Extra: cloud
Requires-Dist: apache-libcloud (>=2.3.0) ; extra == 'cloud'
Provides-Extra: docker
Requires-Dist: docker (>=2.4.2) ; extra == 'docker'
